zxl.py
zxl-1.0.dist-info/METADATA
zxl-1.0.dist-info/WHEEL
zxl-1.0.dist-info/top_level.txt
zxl-1.0.dist-info/RECORD
