Metadata-Version: 2.1
Name: zxl
Version: 1.0
Summary: for love
Home-page: https://github.com/upuuuuuu
Author: upuuuuuu
Author-email: 2226548059@qq.com
License: MIT
